pyproject.toml
setup.cfg
setup.py
qwery_core/__init__.py
qwery_core/launcher.py
qwery_core.egg-info/PKG-INFO
qwery_core.egg-info/SOURCES.txt
qwery_core.egg-info/dependency_links.txt
qwery_core.egg-info/entry_points.txt
qwery_core.egg-info/top_level.txt
qwery_core/bin/android/Devil
qwery_core/bin/ish/Devil