Metadata-Version: 2.1
Name: qwery-core
Version: 1.0.7
Summary: Qwery Core Binary Runner
Home-page: https://t.me/NexLangPy
Author: DEVIL
Author-email: pxgito@gmail.com
Requires-Python: >=3.7
